CHANGES.rst
MANIFEST.in
README.rst
setup.py
docs/LICENSE-GPL.rst
src/bda/__init__.py
src/bda.portlet.sitenavigation.egg-info/PKG-INFO
src/bda.portlet.sitenavigation.egg-info/SOURCES.txt
src/bda.portlet.sitenavigation.egg-info/dependency_links.txt
src/bda.portlet.sitenavigation.egg-info/namespace_packages.txt
src/bda.portlet.sitenavigation.egg-info/not-zip-safe
src/bda.portlet.sitenavigation.egg-info/requires.txt
src/bda.portlet.sitenavigation.egg-info/top_level.txt
src/bda/portlet/__init__.py
src/bda/portlet/sitenavigation/__init__.py
src/bda/portlet/sitenavigation/configure.zcml
src/bda/portlet/sitenavigation/interfaces.py
src/bda/portlet/sitenavigation/sitenavigation.pt
src/bda/portlet/sitenavigation/sitenavigation.py
src/bda/portlet/sitenavigation/sitenavigation_recurse.pt
src/bda/portlet/sitenavigation/vocabularies.py
src/bda/portlet/sitenavigation/locales/MARKER
src/bda/portlet/sitenavigation/profiles/default/metadata.xml
src/bda/portlet/sitenavigation/profiles/default/portlets.xml
src/bda/portlet/sitenavigation/profiles/uninstall/portlets.xml
src/bda/portlet/sitenavigation/upgrades/__init__.py
src/bda/portlet/sitenavigation/upgrades/configure.zcml