Metadata-Version: 1.1
Name: bda.portlet.sitenavigation
Version: 2.0
Summary: Yet Another Navigation Portlet.
Home-page: http://github.com/bda/bda.portlet.sitenavigation
Author: Johannes Raggam
Author-email: johannes@raggam.co.at
License: GPL
Keywords: plone portlet
Platform: UNKNOWN
Classifier: Framework :: Plone
Classifier: Programming Language :: Python
